run_subprocess.py
run_subprocess-0.9.1.dist-info/LICENSE
run_subprocess-0.9.1.dist-info/METADATA
run_subprocess-0.9.1.dist-info/WHEEL
run_subprocess-0.9.1.dist-info/top_level.txt
run_subprocess-0.9.1.dist-info/RECORD
